legion_code_generator/__init__.py
legion_code_generator/__main__.py
legion_code_generator/agent.py
legion_code_generator/context.py
legion_code_generator/executor.py
legion_code_generator/llm.py
legion_code_generator/prompts.py
legion_code_generator/utils.py
legion_code_generator-0.1.6.dist-info/licenses/LICENSE
legion_code_generator-0.1.6.dist-info/METADATA
legion_code_generator-0.1.6.dist-info/WHEEL
legion_code_generator-0.1.6.dist-info/entry_points.txt
legion_code_generator-0.1.6.dist-info/top_level.txt
legion_code_generator-0.1.6.dist-info/RECORD
