Metadata-Version: 2.4
Name: legion-code-generator
Version: 0.1.6
Summary: A terminal-based AI coding agent for assisting with development tasks
Author: Legion/Chinmay Singh
Author-email: Legion/Chinmay Singh <chinmaysingh619@gmail.com>
Keywords: ai,code,generator,terminal,development,gpt,openai,gemini
Classifier: Programming Language :: Python :: 3
Classifier: Programming Language :: Python :: 3.8
Classifier: Programming Language :: Python :: 3.9
Classifier: Programming Language :: Python :: 3.10
Classifier: License :: OSI Approved :: MIT License
Classifier: Operating System :: OS Independent
Classifier: Development Status :: 4 - Beta
Classifier: Intended Audience :: Developers
Classifier: Topic :: Software Development :: Code Generators
Requires-Python: >=3.8
License-File: LICENSE
Requires-Dist: openai>=1.0.0
Requires-Dist: python-dotenv>=1.0.0
Requires-Dist: termcolor>=2.3.0
Requires-Dist: pytest>=7.4.0
Requires-Dist: setuptools>=42.0.0
Requires-Dist: pathlib>=1.0.1
Requires-Dist: typing-extensions>=4.0.0
Requires-Dist: rich>=13.7.0
Dynamic: author
Dynamic: license-file
Dynamic: requires-python
